mcpMQTT/app/__init__.py
mcpMQTT/app/mcp_server.py
mcpMQTT/app/mqtt_client.py
mcpMQTT/config/config_manager.py
mcpMQTT/config/schema.py
mcpmqtt-0.0.2.dist-info/licenses/LICENSE.md
mcpmqtt-0.0.2.dist-info/METADATA
mcpmqtt-0.0.2.dist-info/WHEEL
mcpmqtt-0.0.2.dist-info/entry_points.txt
mcpmqtt-0.0.2.dist-info/top_level.txt
mcpmqtt-0.0.2.dist-info/RECORD
