Metadata-Version: 2.4
Name: mcpMQTT
Version: 0.0.2
Summary: An MCP server for basic MQTT operations
Author-email: Thomas Spielauer <pypipackages01@tspi.at>
Project-URL: Homepage, https://github.com/tspspi/mcpMQTT
Requires-Python: >=3.11
License-File: LICENSE.md
Requires-Dist: paho-mqtt>=1.6.1
Requires-Dist: mcp>=1.0.0
Requires-Dist: pydantic>2.5.0
Dynamic: license-file
